weblair/__init__.py
weblair/autogui.py
weblair/weblair.py
weblair/weblair_extended.py
weblair/weblair_sync.py
weblair-0.0.15.dist-info/METADATA
weblair-0.0.15.dist-info/WHEEL
weblair-0.0.15.dist-info/RECORD
